partboost/__init__.py
partboost-0.0.1.dist-info/LICENSE
partboost-0.0.1.dist-info/METADATA
partboost-0.0.1.dist-info/WHEEL
partboost-0.0.1.dist-info/top_level.txt
partboost-0.0.1.dist-info/RECORD
