Metadata-Version: 2.1
Name: partboost
Version: 0.0.1
Summary: Simplified Partlet Boosting
Home-page: https://github.com/partletboost/partboost
Author: Alex Fedotov
Author-email: alex.fedotov@aol.com
License: UNKNOWN
Platform: UNKNOWN
Classifier: Programming Language :: Python :: 3
Classifier: License :: OSI Approved :: MIT License
Classifier: Operating System :: OS Independent
Requires-Python: >=3.7
